rhealpixdggs/.coverage
rhealpixdggs/__init__.py
rhealpixdggs/cell.py
rhealpixdggs/conversion.py
rhealpixdggs/dggs.py
rhealpixdggs/ellipsoids.py
rhealpixdggs/pj_healpix.py
rhealpixdggs/pj_rhealpix.py
rhealpixdggs/projection_wrapper.py
rhealpixdggs/rhp_wrappers.py
rhealpixdggs/utils.py
rhealpixdggs-0.5.13.dist-info/LICENSE
rhealpixdggs-0.5.13.dist-info/LICENSE-LGPL
rhealpixdggs-0.5.13.dist-info/LICENSE-MIT
rhealpixdggs-0.5.13.dist-info/METADATA
rhealpixdggs-0.5.13.dist-info/WHEEL
rhealpixdggs-0.5.13.dist-info/RECORD
