Metadata-Version: 2.3
Name: rHEALPixDGGS
Version: 0.5.13
Summary: An implementation of the rHEALPix discrete global grid system
License: GPL-3.0-or-later
Keywords: DGGS,Discrete Global Grid System,reference system,spatial,geospatial
Author: Alexander Raichev
Author-email: alex@raichev.net
Requires-Python: >=3.11
Classifier: Development Status :: 4 - Beta
Classifier: Topic :: Utilities
Classifier: Intended Audience :: Developers
Classifier: Natural Language :: English
Classifier: Programming Language :: Python :: 3
Classifier: Programming Language :: Python :: 3 :: Only
Classifier: Programming Language :: Python :: 3.11
Classifier: Programming Language :: Python :: Implementation :: CPython
Classifier: Programming Language :: Python :: Implementation :: PyPy
Classifier: Topic :: Software Development :: Libraries :: Python Modules
Requires-Dist: matplotlib (>=3.7)
Requires-Dist: numpy (>=2.0)
Requires-Dist: pyproj (>=3.6)
Requires-Dist: scipy (>=1.11)
Requires-Dist: shapely (>=2.1)
Project-URL: bug_reports, https://github.com/manaakiwhenua/rhealpixdggs-py/issues
Project-URL: source, https://github.com/manaakiwhenua/rhealpixdggs-py
